<?xml version="1.0" encoding="UTF-8" ?>
<!DOCTYPE mapper PUBLIC "-//mybatis.org//DTD Mapper 3.0//EN" "http://mybatis.org/dtd/mybatis-3-mapper.dtd" >
<mapper namespace="com.cibr.animal.demo.dao.CibrBillLibMapper" >
  <resultMap id="BaseResultMap" type="com.cibr.animal.demo.entity.CibrBillLib" >
    <!--
      WARNING - @mbggenerated
      This element is automatically generated by MyBatis Generator, do not modify.
    -->
    <id column="id" property="id" jdbcType="VARCHAR" />
    <result column="billId" property="billid" jdbcType="VARCHAR" />
    <result column="processId" property="processid" jdbcType="VARCHAR" />
    <result column="processName" property="processname" jdbcType="VARCHAR" />
    <result column="userName" property="username" jdbcType="VARCHAR" />
    <result column="userId" property="userid" jdbcType="VARCHAR" />
    <result column="libId" property="libid" jdbcType="VARCHAR" />
    <result column="libName" property="libname" jdbcType="VARCHAR" />
    <result column="libPrice" property="libprice" jdbcType="DECIMAL" />
    <result column="libCount" property="libcount" jdbcType="DECIMAL" />
    <result column="libTotal" property="libtotal" jdbcType="DECIMAL" />
    <result column="libStatu" property="libstatu" jdbcType="VARCHAR" />
    <result column="groupId" property="groupid" jdbcType="VARCHAR" />
    <result column="groupName" property="groupname" jdbcType="VARCHAR" />
    <result column="creater" property="creater" jdbcType="VARCHAR" />
    <result column="createTime" property="createtime" jdbcType="TIMESTAMP" />
    <result column="updatar" property="updatar" jdbcType="VARCHAR" />
    <result column="updateTime" property="updatetime" jdbcType="TIMESTAMP" />
    <result column="remark" property="remark" jdbcType="VARCHAR" />
    <result column="currentMonth" property="currentmonth" jdbcType="VARCHAR" />
  </resultMap>
  <sql id="Example_Where_Clause" >
    <!--
      WARNING - @mbggenerated
      This element is automatically generated by MyBatis Generator, do not modify.
    -->
    <where >
      <foreach collection="oredCriteria" item="criteria" separator="or" >
        <if test="criteria.valid" >
          <trim prefix="(" suffix=")" prefixOverrides="and" >
            <foreach collection="criteria.criteria" item="criterion" >
              <choose >
                <when test="criterion.noValue" >
                  and ${criterion.condition}
                </when>
                <when test="criterion.singleValue" >
                  and ${criterion.condition} #{criterion.value}
                </when>
                <when test="criterion.betweenValue" >
                  and ${criterion.condition} #{criterion.value} and #{criterion.secondValue}
                </when>
                <when test="criterion.listValue" >
                  and ${criterion.condition}
                  <foreach collection="criterion.value" item="listItem" open="(" close=")" separator="," >
                    #{listItem}
                  </foreach>
                </when>
              </choose>
            </foreach>
          </trim>
        </if>
      </foreach>
    </where>
  </sql>
  <sql id="Update_By_Example_Where_Clause" >
    <!--
      WARNING - @mbggenerated
      This element is automatically generated by MyBatis Generator, do not modify.
    -->
    <where >
      <foreach collection="example.oredCriteria" item="criteria" separator="or" >
        <if test="criteria.valid" >
          <trim prefix="(" suffix=")" prefixOverrides="and" >
            <foreach collection="criteria.criteria" item="criterion" >
              <choose >
                <when test="criterion.noValue" >
                  and ${criterion.condition}
                </when>
                <when test="criterion.singleValue" >
                  and ${criterion.condition} #{criterion.value}
                </when>
                <when test="criterion.betweenValue" >
                  and ${criterion.condition} #{criterion.value} and #{criterion.secondValue}
                </when>
                <when test="criterion.listValue" >
                  and ${criterion.condition}
                  <foreach collection="criterion.value" item="listItem" open="(" close=")" separator="," >
                    #{listItem}
                  </foreach>
                </when>
              </choose>
            </foreach>
          </trim>
        </if>
      </foreach>
    </where>
  </sql>
  <sql id="Base_Column_List" >
    <!--
      WARNING - @mbggenerated
      This element is automatically generated by MyBatis Generator, do not modify.
    -->
    id, billId, processId, processName, userName, userId, libId, libName, libPrice, libCount, 
    libTotal, libStatu, groupId, groupName, creater, createTime, updatar, updateTime, 
    remark, currentMonth
  </sql>
  <select id="selectByExample" resultMap="BaseResultMap" parameterType="com.cibr.animal.demo.entity.CibrBillLibExample" >
    <!--
      WARNING - @mbggenerated
      This element is automatically generated by MyBatis Generator, do not modify.
    -->
    select
    <if test="distinct" >
      distinct
    </if>
    <include refid="Base_Column_List" />
    from cibr_bill_lib
    <if test="_parameter != null" >
      <include refid="Example_Where_Clause" />
    </if>
    <if test="orderByClause != null" >
      order by ${orderByClause}
    </if>
  </select>
  <select id="selectByPrimaryKey" resultMap="BaseResultMap" parameterType="java.lang.String" >
    <!--
      WARNING - @mbggenerated
      This element is automatically generated by MyBatis Generator, do not modify.
    -->
    select 
    <include refid="Base_Column_List" />
    from cibr_bill_lib
    where id = #{id,jdbcType=VARCHAR}
  </select>
  <delete id="deleteByPrimaryKey" parameterType="java.lang.String" >
    <!--
      WARNING - @mbggenerated
      This element is automatically generated by MyBatis Generator, do not modify.
    -->
    delete from cibr_bill_lib
    where id = #{id,jdbcType=VARCHAR}
  </delete>
  <delete id="deleteByExample" parameterType="com.cibr.animal.demo.entity.CibrBillLibExample" >
    <!--
      WARNING - @mbggenerated
      This element is automatically generated by MyBatis Generator, do not modify.
    -->
    delete from cibr_bill_lib
    <if test="_parameter != null" >
      <include refid="Example_Where_Clause" />
    </if>
  </delete>
  <insert id="insert" parameterType="com.cibr.animal.demo.entity.CibrBillLib" >
    <!--
      WARNING - @mbggenerated
      This element is automatically generated by MyBatis Generator, do not modify.
    -->
    insert into cibr_bill_lib (id, billId, processId, 
      processName, userName, userId, 
      libId, libName, libPrice, 
      libCount, libTotal, libStatu, 
      groupId, groupName, creater, 
      createTime, updatar, updateTime, 
      remark, currentMonth)
    values (#{id,jdbcType=VARCHAR}, #{billid,jdbcType=VARCHAR}, #{processid,jdbcType=VARCHAR}, 
      #{processname,jdbcType=VARCHAR}, #{username,jdbcType=VARCHAR}, #{userid,jdbcType=VARCHAR}, 
      #{libid,jdbcType=VARCHAR}, #{libname,jdbcType=VARCHAR}, #{libprice,jdbcType=DECIMAL}, 
      #{libcount,jdbcType=DECIMAL}, #{libtotal,jdbcType=DECIMAL}, #{libstatu,jdbcType=VARCHAR}, 
      #{groupid,jdbcType=VARCHAR}, #{groupname,jdbcType=VARCHAR}, #{creater,jdbcType=VARCHAR}, 
      #{createtime,jdbcType=TIMESTAMP}, #{updatar,jdbcType=VARCHAR}, #{updatetime,jdbcType=TIMESTAMP}, 
      #{remark,jdbcType=VARCHAR}, #{currentmonth,jdbcType=VARCHAR})
  </insert>
  <insert id="insertSelective" parameterType="com.cibr.animal.demo.entity.CibrBillLib" >
    <!--
      WARNING - @mbggenerated
      This element is automatically generated by MyBatis Generator, do not modify.
    -->
    insert into cibr_bill_lib
    <trim prefix="(" suffix=")" suffixOverrides="," >
      <if test="id != null" >
        id,
      </if>
      <if test="billid != null" >
        billId,
      </if>
      <if test="processid != null" >
        processId,
      </if>
      <if test="processname != null" >
        processName,
      </if>
      <if test="username != null" >
        userName,
      </if>
      <if test="userid != null" >
        userId,
      </if>
      <if test="libid != null" >
        libId,
      </if>
      <if test="libname != null" >
        libName,
      </if>
      <if test="libprice != null" >
        libPrice,
      </if>
      <if test="libcount != null" >
        libCount,
      </if>
      <if test="libtotal != null" >
        libTotal,
      </if>
      <if test="libstatu != null" >
        libStatu,
      </if>
      <if test="groupid != null" >
        groupId,
      </if>
      <if test="groupname != null" >
        groupName,
      </if>
      <if test="creater != null" >
        creater,
      </if>
      <if test="createtime != null" >
        createTime,
      </if>
      <if test="updatar != null" >
        updatar,
      </if>
      <if test="updatetime != null" >
        updateTime,
      </if>
      <if test="remark != null" >
        remark,
      </if>
      <if test="currentmonth != null" >
        currentMonth,
      </if>
    </trim>
    <trim prefix="values (" suffix=")" suffixOverrides="," >
      <if test="id != null" >
        #{id,jdbcType=VARCHAR},
      </if>
      <if test="billid != null" >
        #{billid,jdbcType=VARCHAR},
      </if>
      <if test="processid != null" >
        #{processid,jdbcType=VARCHAR},
      </if>
      <if test="processname != null" >
        #{processname,jdbcType=VARCHAR},
      </if>
      <if test="username != null" >
        #{username,jdbcType=VARCHAR},
      </if>
      <if test="userid != null" >
        #{userid,jdbcType=VARCHAR},
      </if>
      <if test="libid != null" >
        #{libid,jdbcType=VARCHAR},
      </if>
      <if test="libname != null" >
        #{libname,jdbcType=VARCHAR},
      </if>
      <if test="libprice != null" >
        #{libprice,jdbcType=DECIMAL},
      </if>
      <if test="libcount != null" >
        #{libcount,jdbcType=DECIMAL},
      </if>
      <if test="libtotal != null" >
        #{libtotal,jdbcType=DECIMAL},
      </if>
      <if test="libstatu != null" >
        #{libstatu,jdbcType=VARCHAR},
      </if>
      <if test="groupid != null" >
        #{groupid,jdbcType=VARCHAR},
      </if>
      <if test="groupname != null" >
        #{groupname,jdbcType=VARCHAR},
      </if>
      <if test="creater != null" >
        #{creater,jdbcType=VARCHAR},
      </if>
      <if test="createtime != null" >
        #{createtime,jdbcType=TIMESTAMP},
      </if>
      <if test="updatar != null" >
        #{updatar,jdbcType=VARCHAR},
      </if>
      <if test="updatetime != null" >
        #{updatetime,jdbcType=TIMESTAMP},
      </if>
      <if test="remark != null" >
        #{remark,jdbcType=VARCHAR},
      </if>
      <if test="currentmonth != null" >
        #{currentmonth,jdbcType=VARCHAR},
      </if>
    </trim>
  </insert>
  <select id="countByExample" parameterType="com.cibr.animal.demo.entity.CibrBillLibExample" resultType="java.lang.Integer" >
    <!--
      WARNING - @mbggenerated
      This element is automatically generated by MyBatis Generator, do not modify.
    -->
    select count(*) from cibr_bill_lib
    <if test="_parameter != null" >
      <include refid="Example_Where_Clause" />
    </if>
  </select>
  <update id="updateByExampleSelective" parameterType="map" >
    <!--
      WARNING - @mbggenerated
      This element is automatically generated by MyBatis Generator, do not modify.
    -->
    update cibr_bill_lib
    <set >
      <if test="record.id != null" >
        id = #{record.id,jdbcType=VARCHAR},
      </if>
      <if test="record.billid != null" >
        billId = #{record.billid,jdbcType=VARCHAR},
      </if>
      <if test="record.processid != null" >
        processId = #{record.processid,jdbcType=VARCHAR},
      </if>
      <if test="record.processname != null" >
        processName = #{record.processname,jdbcType=VARCHAR},
      </if>
      <if test="record.username != null" >
        userName = #{record.username,jdbcType=VARCHAR},
      </if>
      <if test="record.userid != null" >
        userId = #{record.userid,jdbcType=VARCHAR},
      </if>
      <if test="record.libid != null" >
        libId = #{record.libid,jdbcType=VARCHAR},
      </if>
      <if test="record.libname != null" >
        libName = #{record.libname,jdbcType=VARCHAR},
      </if>
      <if test="record.libprice != null" >
        libPrice = #{record.libprice,jdbcType=DECIMAL},
      </if>
      <if test="record.libcount != null" >
        libCount = #{record.libcount,jdbcType=DECIMAL},
      </if>
      <if test="record.libtotal != null" >
        libTotal = #{record.libtotal,jdbcType=DECIMAL},
      </if>
      <if test="record.libstatu != null" >
        libStatu = #{record.libstatu,jdbcType=VARCHAR},
      </if>
      <if test="record.groupid != null" >
        groupId = #{record.groupid,jdbcType=VARCHAR},
      </if>
      <if test="record.groupname != null" >
        groupName = #{record.groupname,jdbcType=VARCHAR},
      </if>
      <if test="record.creater != null" >
        creater = #{record.creater,jdbcType=VARCHAR},
      </if>
      <if test="record.createtime != null" >
        createTime = #{record.createtime,jdbcType=TIMESTAMP},
      </if>
      <if test="record.updatar != null" >
        updatar = #{record.updatar,jdbcType=VARCHAR},
      </if>
      <if test="record.updatetime != null" >
        updateTime = #{record.updatetime,jdbcType=TIMESTAMP},
      </if>
      <if test="record.remark != null" >
        remark = #{record.remark,jdbcType=VARCHAR},
      </if>
      <if test="record.currentmonth != null" >
        currentMonth = #{record.currentmonth,jdbcType=VARCHAR},
      </if>
    </set>
    <if test="_parameter != null" >
      <include refid="Update_By_Example_Where_Clause" />
    </if>
  </update>
  <update id="updateByExample" parameterType="map" >
    <!--
      WARNING - @mbggenerated
      This element is automatically generated by MyBatis Generator, do not modify.
    -->
    update cibr_bill_lib
    set id = #{record.id,jdbcType=VARCHAR},
      billId = #{record.billid,jdbcType=VARCHAR},
      processId = #{record.processid,jdbcType=VARCHAR},
      processName = #{record.processname,jdbcType=VARCHAR},
      userName = #{record.username,jdbcType=VARCHAR},
      userId = #{record.userid,jdbcType=VARCHAR},
      libId = #{record.libid,jdbcType=VARCHAR},
      libName = #{record.libname,jdbcType=VARCHAR},
      libPrice = #{record.libprice,jdbcType=DECIMAL},
      libCount = #{record.libcount,jdbcType=DECIMAL},
      libTotal = #{record.libtotal,jdbcType=DECIMAL},
      libStatu = #{record.libstatu,jdbcType=VARCHAR},
      groupId = #{record.groupid,jdbcType=VARCHAR},
      groupName = #{record.groupname,jdbcType=VARCHAR},
      creater = #{record.creater,jdbcType=VARCHAR},
      createTime = #{record.createtime,jdbcType=TIMESTAMP},
      updatar = #{record.updatar,jdbcType=VARCHAR},
      updateTime = #{record.updatetime,jdbcType=TIMESTAMP},
      remark = #{record.remark,jdbcType=VARCHAR},
      currentMonth = #{record.currentmonth,jdbcType=VARCHAR}
    <if test="_parameter != null" >
      <include refid="Update_By_Example_Where_Clause" />
    </if>
  </update>
  <update id="updateByPrimaryKeySelective" parameterType="com.cibr.animal.demo.entity.CibrBillLib" >
    <!--
      WARNING - @mbggenerated
      This element is automatically generated by MyBatis Generator, do not modify.
    -->
    update cibr_bill_lib
    <set >
      <if test="billid != null" >
        billId = #{billid,jdbcType=VARCHAR},
      </if>
      <if test="processid != null" >
        processId = #{processid,jdbcType=VARCHAR},
      </if>
      <if test="processname != null" >
        processName = #{processname,jdbcType=VARCHAR},
      </if>
      <if test="username != null" >
        userName = #{username,jdbcType=VARCHAR},
      </if>
      <if test="userid != null" >
        userId = #{userid,jdbcType=VARCHAR},
      </if>
      <if test="libid != null" >
        libId = #{libid,jdbcType=VARCHAR},
      </if>
      <if test="libname != null" >
        libName = #{libname,jdbcType=VARCHAR},
      </if>
      <if test="libprice != null" >
        libPrice = #{libprice,jdbcType=DECIMAL},
      </if>
      <if test="libcount != null" >
        libCount = #{libcount,jdbcType=DECIMAL},
      </if>
      <if test="libtotal != null" >
        libTotal = #{libtotal,jdbcType=DECIMAL},
      </if>
      <if test="libstatu != null" >
        libStatu = #{libstatu,jdbcType=VARCHAR},
      </if>
      <if test="groupid != null" >
        groupId = #{groupid,jdbcType=VARCHAR},
      </if>
      <if test="groupname != null" >
        groupName = #{groupname,jdbcType=VARCHAR},
      </if>
      <if test="creater != null" >
        creater = #{creater,jdbcType=VARCHAR},
      </if>
      <if test="createtime != null" >
        createTime = #{createtime,jdbcType=TIMESTAMP},
      </if>
      <if test="updatar != null" >
        updatar = #{updatar,jdbcType=VARCHAR},
      </if>
      <if test="updatetime != null" >
        updateTime = #{updatetime,jdbcType=TIMESTAMP},
      </if>
      <if test="remark != null" >
        remark = #{remark,jdbcType=VARCHAR},
      </if>
      <if test="currentmonth != null" >
        currentMonth = #{currentmonth,jdbcType=VARCHAR},
      </if>
    </set>
    where id = #{id,jdbcType=VARCHAR}
  </update>
  <update id="updateByPrimaryKey" parameterType="com.cibr.animal.demo.entity.CibrBillLib" >
    <!--
      WARNING - @mbggenerated
      This element is automatically generated by MyBatis Generator, do not modify.
    -->
    update cibr_bill_lib
    set billId = #{billid,jdbcType=VARCHAR},
      processId = #{processid,jdbcType=VARCHAR},
      processName = #{processname,jdbcType=VARCHAR},
      userName = #{username,jdbcType=VARCHAR},
      userId = #{userid,jdbcType=VARCHAR},
      libId = #{libid,jdbcType=VARCHAR},
      libName = #{libname,jdbcType=VARCHAR},
      libPrice = #{libprice,jdbcType=DECIMAL},
      libCount = #{libcount,jdbcType=DECIMAL},
      libTotal = #{libtotal,jdbcType=DECIMAL},
      libStatu = #{libstatu,jdbcType=VARCHAR},
      groupId = #{groupid,jdbcType=VARCHAR},
      groupName = #{groupname,jdbcType=VARCHAR},
      creater = #{creater,jdbcType=VARCHAR},
      createTime = #{createtime,jdbcType=TIMESTAMP},
      updatar = #{updatar,jdbcType=VARCHAR},
      updateTime = #{updatetime,jdbcType=TIMESTAMP},
      remark = #{remark,jdbcType=VARCHAR},
      currentMonth = #{currentmonth,jdbcType=VARCHAR}
    where id = #{id,jdbcType=VARCHAR}
  </update>
</mapper>